pykinect/LICENSE.txt
pykinect/__init__.py
pykinect/audio/PyKinectAudio.dll
pykinect/audio/__init__.py
pykinect/nui/structs.py
pykinect/nui/_interop.py
pykinect/nui/__init__.py
pykinect-2.1.dist-info/DESCRIPTION.rst
pykinect-2.1.dist-info/METADATA
pykinect-2.1.dist-info/metadata.json
pykinect-2.1.dist-info/RECORD
pykinect-2.1.dist-info/top_level.txt
pykinect-2.1.dist-info/WHEEL
winspeech/LICENSE.txt
winspeech/recognition.py
winspeech/__init__.py
