Metadata-Version: 1.1
Name: pykinect
Version: 2.1
Summary: PyKinect Module for interacting with the Kinect SDK
Home-page: http://pytools.codeplex.com/
Author: Microsoft Corporation
Author-email: ptvshelp@microsoft.com
License: UNKNOWN
Platform: win32
Classifier: Development Status :: 5 - Production/Stable
Classifier: Environment :: Win32 (MS Windows)
Classifier: License :: OSI Approved :: Apache Software License
Classifier: Natural Language :: English
Classifier: Operating System :: Microsoft :: Windows
Classifier: Operating System :: Microsoft :: Windows :: Windows 7
Classifier: Programming Language :: C++
Classifier: Programming Language :: Python
Classifier: Programming Language :: Python :: 2.7
Classifier: Programming Language :: Python :: 2 :: Only
Classifier: Topic :: Games/Entertainment
Classifier: Topic :: Multimedia :: Graphics
Classifier: Topic :: Multimedia :: Graphics :: Capture
Classifier: Topic :: Multimedia :: Sound/Audio
